faculty_sphinx_theme/__init__.py
faculty_sphinx_theme/breadcrumbs.html
faculty_sphinx_theme/layout.html
faculty_sphinx_theme/theme.conf
faculty_sphinx_theme/static/css/faculty.css
faculty_sphinx_theme/static/images/faculty.svg
faculty_sphinx_theme/static/images/favicon.ico
faculty_sphinx_theme-0.3.1.dist-info/LICENSE-2.0.txt
faculty_sphinx_theme-0.3.1.dist-info/METADATA
faculty_sphinx_theme-0.3.1.dist-info/WHEEL
faculty_sphinx_theme-0.3.1.dist-info/entry_points.txt
faculty_sphinx_theme-0.3.1.dist-info/top_level.txt
faculty_sphinx_theme-0.3.1.dist-info/RECORD
