Metadata-Version: 2.1
Name: faculty-sphinx-theme
Version: 0.3.1
Summary: A Sphinx theme for Faculty projects.
Home-page: UNKNOWN
Author: Faculty
Author-email: opensource@faculty.ai
License: Apache Software License
Platform: UNKNOWN
Requires-Dist: sphinx-rtd-theme (==0.4.3)
